[
  {
    "identifier": "0000001",
    "name": "Gene Product Has Function",
    "transitive": false,
    "creator": "0000-0003-4423-4370"
  },
  {
    "identifier": "0000002",
    "name": "Has Mature miRNA",
    "transitive": false,
    "creator": "0000-0003-4423-4370"
  },
  {
    "identifier": "0000003",
    "name": "Species Specific",
    "transitive": false,
    "creator": "0000-0003-4423-4370"
  },
  {
    "identifier": "0000004",
    "name": "Antibody has target",
    "transitive": false,
    "creator": "0000-0003-4423-4370"
  }
]